{"NKNUSDT": {"buy": {"exchange": "Huobi", "rate": "0.107581406"}, "sell": {"exchange": "Mexc", "rate": "0.1059114"}, "profit": 1.58}, "XENUSDT": {"buy": {"exchange": "Huobi", "rate": "0.0000012375"}, "sell": {"exchange": "Mexc", "rate": "0.0000011723"}, "profit": 5.56}, "CAWUSDT": {"sell": {"exchange": "Huobi", "rate": "0.0000000595"}, "buy": {"exchange": "Mexc", "rate": "0.0000000603"}, "profit": 1.35}, "CAREUSDT": {"buy": {"exchange": "Kucoin", "rate": "0.0056951991"}, "sell": {"exchange": "Gateio", "rate": "0.005594166"}, "profit": 1.81}, "BRISEUSDT": {"buy": {"exchange": "Kucoin", "rate": "0.0000005266"}, "sell": {"exchange": "Gateio", "rate": "0.0000005084"}, "profit": 3.58}, "BABYDOGEUSDT": {"buy": {"exchange": "Mexc", "rate": "0.0000000021"}, "sell": {"exchange": "Okx", "rate": "0.000000002"}, "profit": 6.54}, "REELTUSDT": {"sell": {"exchange": "Gateio", "rate": "0.025769436"}, "buy": {"exchange": "Mexc", "rate": "0.02726536"}, "profit": 5.81}}