{"TOMIUSDT": {"buy": {"exchange": "Huobi", "rate": "3.0938"}, "sell": {"exchange": "Gateio", "rate": "3.05521824"}, "profit": 1.26}, "MCGUSDT": {"buy": {"exchange": "Huobi", "rate": "0.1078339"}, "sell": {"exchange": "Gateio", "rate": "0.10473906"}, "profit": 2.95}, "ALIUSDT": {"sell": {"exchange": "Huobi", "rate": "0.039096036"}, "buy": {"exchange": "Gateio", "rate": "0.039647546"}, "profit": 1.41}, "INSURUSDT": {"buy": {"exchange": "Huobi", "rate": "0.0769458"}, "sell": {"exchange": "Mexc", "rate": "0.0758514"}, "profit": 1.44}, "CAWUSDT": {"sell": {"exchange": "Huobi", "rate": "0.0000000595"}, "buy": {"exchange": "Mexc", "rate": "0.0000000605"}, "profit": 1.64}, "KINGUSDT": {"sell": {"exchange": "Kucoin", "rate": "0.0135135"}, "buy": {"exchange": "Gateio", "rate": "0.013733478"}, "profit": 1.63}, "PIASUSDT": {"buy": {"exchange": "Kucoin", "rate": "0.01514484"}, "sell": {"exchange": "Gateio", "rate": "0.01491978"}, "profit": 1.51}, "MANUSDT": {"buy": {"exchange": "Kucoin", "rate": "0.043996959"}, "sell": {"exchange": "Gateio", "rate": "0.041300436"}, "profit": 6.53}, "BRISEUSDT": {"buy": {"exchange": "Kucoin", "rate": "0.0000005351"}, "sell": {"exchange": "Gateio", "rate": "0.0000005169"}, "profit": 3.51}, "GMMUSDT": {"sell": {"exchange": "Kucoin", "rate": "0.0016644628"}, "buy": {"exchange": "Mexc", "rate": "0.0016835262"}, "profit": 1.15}, "REELTUSDT": {"sell": {"exchange": "Gateio", "rate": "0.025679256"}, "buy": {"exchange": "Mexc", "rate": "0.0275947"}, "profit": 7.46}, "BABYDOGEUSDT": {"buy": {"exchange": "Mexc", "rate": "0.0000000021"}, "sell": {"exchange": "Okx", "rate": "0.000000002"}, "profit": 6.34}}