{"MCUSDT": {"buy": {"exchange": "Binance", "rate": "0.291708"}, "sell": {"exchange": "Kucoin", "rate": "0.26602576"}, "profit": 9.65}, "EGAMEUSDT": {"buy": {"exchange": "Huobi", "rate": "0.0001183329"}, "sell": {"exchange": "Kucoin", "rate": "0.0001156055"}, "profit": 2.36}, "BRISEUSDT": {"sell": {"exchange": "Gateio", "rate": "0.0000004707"}, "buy": {"exchange": "Mexc", "rate": "0.0000005101"}, "profit": 8.37}, "MANUSDT": {"buy": {"exchange": "Kucoin", "rate": "0.04423572"}, "sell": {"exchange": "Gateio", "rate": "0.041605545"}, "profit": 6.32}, "DEVTUSDT": {"buy": {"exchange": "Gateio", "rate": "0.00470058"}, "sell": {"exchange": "Okx", "rate": "0.0046046"}, "profit": 2.08}, "BABYDOGEUSDT": {"sell": {"exchange": "Gateio", "rate": "0.0000000022"}, "buy": {"exchange": "Okx", "rate": "0.0000000024"}, "profit": 8.22}}