{"RAINUSDT": {"buy": {"exchange": "Huobi", "rate": "0.002511966"}, "sell": {"exchange": "Mexc", "rate": "0.00242484"}, "profit": 3.59}, "MANUSDT": {"buy": {"exchange": "Kucoin", "rate": "0.044751204"}, "sell": {"exchange": "Gateio", "rate": "0.0413603556"}, "profit": 8.2}, "LUFFYUSDT": {"sell": {"exchange": "Gateio", "rate": "0.0001181358"}, "buy": {"exchange": "Mexc", "rate": "0.0001256482"}, "profit": 6.36}, "BABYDOGEUSDT": {"buy": {"exchange": "Mexc", "rate": "0.0000000023"}, "sell": {"exchange": "Okx", "rate": "0.0000000022"}, "profit": 5.95}, "RJVUSDT": {"sell": {"exchange": "Gateio", "rate": "0.0937872"}, "buy": {"exchange": "Mexc", "rate": "0.09481"}, "profit": 1.09}}