{"MCGUSDT": {"sell": {"exchange": "Huobi", "rate": "0.08219406"}, "buy": {"exchange": "Gateio", "rate": "0.0840815"}, "profit": 2.3}, "SEELEUSDT": {"buy": {"exchange": "Huobi", "rate": "0.003326334"}, "sell": {"exchange": "Gateio", "rate": "0.003268524"}, "profit": 1.77}, "PIASUSDT": {"buy": {"exchange": "Kucoin", "rate": "0.01469529"}, "sell": {"exchange": "Gateio", "rate": "0.01449894"}, "profit": 1.35}, "MANUSDT": {"buy": {"exchange": "Kucoin", "rate": "0.042788169"}, "sell": {"exchange": "Gateio", "rate": "0.039603048"}, "profit": 8.04}, "BRISEUSDT": {"buy": {"exchange": "Kucoin", "rate": "0.0000005053"}, "sell": {"exchange": "Gateio", "rate": "0.0000004943"}, "profit": 2.22}, "EJSUSDT": {"buy": {"exchange": "Gateio", "rate": "0.00513471"}, "sell": {"exchange": "Mexc", "rate": "0.005043066"}, "profit": 1.82}, "DEVTUSDT": {"sell": {"exchange": "Gateio", "rate": "0.0042084"}, "buy": {"exchange": "Okx", "rate": "0.00435564"}, "profit": 3.5}, "BABYDOGEUSDT": {"buy": {"exchange": "Mexc", "rate": "0.0000000021"}, "sell": {"exchange": "Okx", "rate": "0.000000002"}, "profit": 4.89}}