{"RLCUSDT": {"buy": {"exchange": "Kucoin", "rate": "1.849149"}, "sell": {"exchange": "Mexc", "rate": "1.820634"}, "profit": 1.57}, "SOSUSDT": {"buy": {"exchange": "Kucoin", "rate": "0.0000002128"}, "sell": {"exchange": "Okx", "rate": "0.0000002102"}, "profit": 1.23}, "H2OUSDT": {"sell": {"exchange": "Huobi", "rate": "0.121242"}, "buy": {"exchange": "Kucoin", "rate": "0.1224774"}, "profit": 1.02}, "MANUSDT": {"buy": {"exchange": "Kucoin", "rate": "0.045169785"}, "sell": {"exchange": "Gateio", "rate": "0.0416718774"}, "profit": 8.39}, "CULTUSDT": {"buy": {"exchange": "Kucoin", "rate": "0.0000066543"}, "sell": {"exchange": "Gateio", "rate": "0.000006492"}, "profit": 2.5}, "PIASUSDT": {"buy": {"exchange": "Kucoin", "rate": "0.02045952"}, "sell": {"exchange": "Mexc", "rate": "0.02018028"}, "profit": 1.38}, "FLYUSDT": {"buy": {"exchange": "Kucoin", "rate": "0.001360638"}, "sell": {"exchange": "Mexc", "rate": "0.0013007964"}, "profit": 4.6}, "BABYDOGEUSDT": {"buy": {"exchange": "Mexc", "rate": "0.0000000023"}, "sell": {"exchange": "Okx", "rate": "0.0000000022"}, "profit": 4.07}, "RDNTUSDT": {"sell": {"exchange": "Gateio", "rate": "0.43570968"}, "buy": {"exchange": "Mexc", "rate": "0.4414154"}, "profit": 1.31}}