{"MCUSDT": {"buy": {"exchange": "Binance", "rate": "0.287712"}, "sell": {"exchange": "Kucoin", "rate": "0.26555529"}, "profit": 8.34}, "MCGUSDT": {"sell": {"exchange": "Huobi", "rate": "0.0883764"}, "buy": {"exchange": "Gateio", "rate": "0.089321"}, "profit": 1.07}, "BRISEUSDT": {"sell": {"exchange": "Gateio", "rate": "0.0000004547"}, "buy": {"exchange": "Mexc", "rate": "0.000000489"}, "profit": 7.55}, "GQUSDT": {"buy": {"exchange": "Huobi", "rate": "0.00642712"}, "sell": {"exchange": "Mexc", "rate": "0.006348672"}, "profit": 1.24}, "PIASUSDT": {"buy": {"exchange": "Kucoin", "rate": "0.01473525"}, "sell": {"exchange": "Gateio", "rate": "0.01435866"}, "profit": 2.62}, "MANUSDT": {"buy": {"exchange": "Kucoin", "rate": "0.043571385"}, "sell": {"exchange": "Gateio", "rate": "0.0404483352"}, "profit": 7.72}, "MIRUSDT": {"sell": {"exchange": "Gateio", "rate": "0.10031022"}, "buy": {"exchange": "Okx", "rate": "0.101898"}, "profit": 1.58}, "BABYDOGEUSDT": {"buy": {"exchange": "Mexc", "rate": "0.0000000022"}, "sell": {"exchange": "Okx", "rate": "0.000000002"}, "profit": 7.4}}