{"NEXOUSDT": {"buy": {"exchange": "Binance", "rate": "0.785214"}, "sell": {"exchange": "Gateio", "rate": "0.7758486"}, "profit": 1.21}, "CTCUSDT": {"buy": {"exchange": "Huobi", "rate": "0.3809366"}, "sell": {"exchange": "Mexc", "rate": "0.3770526"}, "profit": 1.03}, "TITANUSDT": {"buy": {"exchange": "Huobi", "rate": "0.060328102"}, "sell": {"exchange": "Kucoin", "rate": "0.05890885"}, "profit": 2.41}, "RDNTUSDT": {"sell": {"exchange": "Gateio", "rate": "0.45543906"}, "buy": {"exchange": "Mexc", "rate": "0.475048"}, "profit": 4.31}, "OGVUSDT": {"buy": {"exchange": "Huobi", "rate": "0.006460054"}, "sell": {"exchange": "Mexc", "rate": "0.00623244"}, "profit": 3.65}, "HNTUSDT": {"buy": {"exchange": "Gateio", "rate": "1.3209528"}, "sell": {"exchange": "Okx", "rate": "1.2915903"}, "profit": 2.27}, "COREUMUSDT": {"sell": {"exchange": "Gateio", "rate": "0.55035852"}, "buy": {"exchange": "Mexc", "rate": "0.5651674"}, "profit": 2.69}, "BABYDOGEUSDT": {"buy": {"exchange": "Mexc", "rate": "0.0000000023"}, "sell": {"exchange": "Okx", "rate": "0.0000000022"}, "profit": 5.06}, "KISHUUSDT": {"sell": {"exchange": "Gateio", "rate": "0.0000000005"}, "buy": {"exchange": "Okx", "rate": "0.0000000005"}, "profit": 1.8}}