{"TITANUSDT": {"buy": {"exchange": "Huobi", "rate": "0.060973808"}, "sell": {"exchange": "Kucoin", "rate": "0.0602602"}, "profit": 1.18}, "SOSUSDT": {"buy": {"exchange": "Huobi", "rate": "0.0000002231"}, "sell": {"exchange": "Okx", "rate": "0.0000002202"}, "profit": 1.29}, "TEMUSDT": {"sell": {"exchange": "Kucoin", "rate": "0.19009991"}, "buy": {"exchange": "Gateio", "rate": "0.19295332"}, "profit": 1.5}, "MANUSDT": {"buy": {"exchange": "Kucoin", "rate": "0.0440559"}, "sell": {"exchange": "Gateio", "rate": "0.0414584514"}, "profit": 6.27}, "CAREUSDT": {"sell": {"exchange": "Kucoin", "rate": "0.0078814736"}, "buy": {"exchange": "Gateio", "rate": "0.007995976"}, "profit": 1.45}, "BABYDOGEUSDT": {"buy": {"exchange": "Mexc", "rate": "0.0000000023"}, "sell": {"exchange": "Okx", "rate": "0.0000000021"}, "profit": 6.57}, "OPTIMUSUSDT": {"sell": {"exchange": "Gateio", "rate": "0.48597"}, "buy": {"exchange": "Mexc", "rate": "0.5001976"}, "profit": 2.93}}