{"NEBLUSDT": {"buy": {"exchange": "Binance", "rate": "1.145853"}, "sell": {"exchange": "Mexc", "rate": "1.133262"}, "profit": 1.11}, "DZOOUSDT": {"sell": {"exchange": "Huobi", "rate": "0.044590002"}, "buy": {"exchange": "Mexc", "rate": "0.04516948"}, "profit": 1.3}, "KINGUSDT": {"buy": {"exchange": "Kucoin", "rate": "0.01736262"}, "sell": {"exchange": "Gateio", "rate": "0.017183298"}, "profit": 1.04}, "SPAUSDT": {"buy": {"exchange": "Kucoin", "rate": "0.007403589"}, "sell": {"exchange": "Gateio", "rate": "0.007313598"}, "profit": 1.23}, "MANUSDT": {"buy": {"exchange": "Kucoin", "rate": "0.047089863"}, "sell": {"exchange": "Gateio", "rate": "0.0438419088"}, "profit": 7.41}, "BABYDOGEUSDT": {"buy": {"exchange": "Mexc", "rate": "0.0000000023"}, "sell": {"exchange": "Okx", "rate": "0.0000000022"}, "profit": 3.42}, "NVIRUSDT": {"buy": {"exchange": "Gateio", "rate": "0.04184115"}, "sell": {"exchange": "Mexc", "rate": "0.0413826"}, "profit": 1.11}, "LUFFYUSDT": {"sell": {"exchange": "Gateio", "rate": "0.0001171338"}, "buy": {"exchange": "Mexc", "rate": "0.0001186622"}, "profit": 1.3}}