{"BETHUSDT": {"sell": {"exchange": "Huobi", "rate": "1701.4461"}, "buy": {"exchange": "Okx", "rate": "1730.40786"}, "profit": 1.7}, "IDUSDT": {"buy": {"exchange": "Gateio", "rate": "0.50898"}, "sell": {"exchange": "Mexc", "rate": "0.49217238"}, "profit": 3.41}, "PIASUSDT": {"buy": {"exchange": "Kucoin", "rate": "0.02013984"}, "sell": {"exchange": "Gateio", "rate": "0.0197394"}, "profit": 2.03}, "MANUSDT": {"buy": {"exchange": "Kucoin", "rate": "0.042202755"}, "sell": {"exchange": "Gateio", "rate": "0.0394911246"}, "profit": 6.87}, "BRISEUSDT": {"buy": {"exchange": "Kucoin", "rate": "0.0000004747"}, "sell": {"exchange": "Gateio", "rate": "0.0000004642"}, "profit": 2.27}, "GRAILUSDT": {"buy": {"exchange": "Kucoin", "rate": "4261.15458"}, "sell": {"exchange": "Mexc", "rate": "4213.11942"}, "profit": 1.14}, "FLYUSDT": {"buy": {"exchange": "Kucoin", "rate": "0.001331667"}, "sell": {"exchange": "Mexc", "rate": "0.0012937824"}, "profit": 2.93}, "BABYDOGEUSDT": {"buy": {"exchange": "Mexc", "rate": "0.0000000022"}, "sell": {"exchange": "Okx", "rate": "0.0000000021"}, "profit": 5.75}, "LUFFYUSDT": {"sell": {"exchange": "Gateio", "rate": "0.000123747"}, "buy": {"exchange": "Mexc", "rate": "0.0001313368"}, "profit": 6.13}, "CELTUSDT": {"buy": {"exchange": "Mexc", "rate": "0.0006461052"}, "sell": {"exchange": "Okx", "rate": "0.000634634"}, "profit": 1.81}}