{"RDNTUSDT": {"buy": {"exchange": "Kucoin", "rate": "0.511488"}, "sell": {"exchange": "Mexc", "rate": "0.4732446"}, "profit": 8.08}, "OGVUSDT": {"buy": {"exchange": "Huobi", "rate": "0.006309356"}, "sell": {"exchange": "Mexc", "rate": "0.00620739"}, "profit": 1.64}, "ETHFUSDT": {"buy": {"exchange": "Huobi", "rate": "0.3354278"}, "sell": {"exchange": "Gateio", "rate": "0.311121"}, "profit": 7.81}, "HNTUSDT": {"buy": {"exchange": "Bybit", "rate": "1.465533"}, "sell": {"exchange": "Kucoin", "rate": "1.450449"}, "profit": 1.04}, "MANUSDT": {"buy": {"exchange": "Kucoin", "rate": "0.046478475"}, "sell": {"exchange": "Gateio", "rate": "0.0425730762"}, "profit": 9.17}, "BABYDOGEUSDT": {"buy": {"exchange": "Mexc", "rate": "0.0000000023"}, "sell": {"exchange": "Okx", "rate": "0.0000000022"}, "profit": 4.84}, "KISHUUSDT": {"sell": {"exchange": "Gateio", "rate": "0.0000000005"}, "buy": {"exchange": "Okx", "rate": "0.0000000005"}, "profit": 1.73}}