{"GNSUSDT": {"buy": {"exchange": "Kucoin", "rate": "8.34165"}, "sell": {"exchange": "Mexc", "rate": "8.247462"}, "profit": 1.14}, "KOKUSDT": {"sell": {"exchange": "Huobi", "rate": "0.0673344"}, "buy": {"exchange": "Kucoin", "rate": "0.0684315"}, "profit": 1.63}, "TITANUSDT": {"sell": {"exchange": "Huobi", "rate": "0.057759288"}, "buy": {"exchange": "Kucoin", "rate": "0.0592407"}, "profit": 2.56}, "UNBUSDT": {"buy": {"exchange": "Huobi", "rate": "0.002024942"}, "sell": {"exchange": "Kucoin", "rate": "0.001992991"}, "profit": 1.6}, "BABYDOGEUSDT": {"buy": {"exchange": "Mexc", "rate": "0.0000000022"}, "sell": {"exchange": "Okx", "rate": "0.0000000021"}, "profit": 5.33}, "BETHUSDT": {"sell": {"exchange": "Huobi", "rate": "1784.38164"}, "buy": {"exchange": "Okx", "rate": "1807.38081"}, "profit": 1.29}, "PIASUSDT": {"buy": {"exchange": "Kucoin", "rate": "0.0194805"}, "sell": {"exchange": "Gateio", "rate": "0.01896786"}, "profit": 2.7}, "MANUSDT": {"buy": {"exchange": "Kucoin", "rate": "0.042253704"}, "sell": {"exchange": "Gateio", "rate": "0.0386438334"}, "profit": 9.34}, "BRISEUSDT": {"buy": {"exchange": "Kucoin", "rate": "0.0000004681"}, "sell": {"exchange": "Gateio", "rate": "0.000000463"}, "profit": 1.11}, "REELTUSDT": {"sell": {"exchange": "Gateio", "rate": "0.0297093"}, "buy": {"exchange": "Mexc", "rate": "0.0305388"}, "profit": 2.79}}