{"BETHUSDT": {"sell": {"exchange": "Huobi", "rate": "1757.02704"}, "buy": {"exchange": "Okx", "rate": "1799.15904"}, "profit": 2.4}, "SYSUSDT": {"buy": {"exchange": "Binance", "rate": "0.1843155"}, "sell": {"exchange": "Kucoin", "rate": "0.1819818"}, "profit": 1.28}, "HAIUSDT": {"buy": {"exchange": "Kucoin", "rate": "0.03931065"}, "sell": {"exchange": "Mexc", "rate": "0.03865716"}, "profit": 1.69}, "PIASUSDT": {"buy": {"exchange": "Kucoin", "rate": "0.0185814"}, "sell": {"exchange": "Gateio", "rate": "0.01832658"}, "profit": 1.39}, "MANUSDT": {"buy": {"exchange": "Kucoin", "rate": "0.041085873"}, "sell": {"exchange": "Gateio", "rate": "0.0381261"}, "profit": 7.76}, "GRAILUSDT": {"sell": {"exchange": "Kucoin", "rate": "3103.1"}, "buy": {"exchange": "Mexc", "rate": "3163.66"}, "profit": 1.95}, "UNOUSDT": {"buy": {"exchange": "Kucoin", "rate": "0.06904089"}, "sell": {"exchange": "Mexc", "rate": "0.06676326"}, "profit": 3.41}, "REELTUSDT": {"sell": {"exchange": "Gateio", "rate": "0.026806506"}, "buy": {"exchange": "Mexc", "rate": "0.02922144"}, "profit": 9.01}, "BABYDOGEUSDT": {"buy": {"exchange": "Mexc", "rate": "0.0000000022"}, "sell": {"exchange": "Okx", "rate": "0.0000000021"}, "profit": 2.85}}