{"ALIUSDT": {"sell": {"exchange": "Huobi", "rate": "0.04023531"}, "buy": {"exchange": "Gateio", "rate": "0.041249336"}, "profit": 2.52}, "MANUSDT": {"buy": {"exchange": "Kucoin", "rate": "0.044164791"}, "sell": {"exchange": "Gateio", "rate": "0.042145623"}, "profit": 4.79}, "UNOUSDT": {"buy": {"exchange": "Kucoin", "rate": "0.06858135"}, "sell": {"exchange": "Mexc", "rate": "0.067134"}, "profit": 2.16}, "BABYDOGEUSDT": {"buy": {"exchange": "Mexc", "rate": "0.0000000023"}, "sell": {"exchange": "Okx", "rate": "0.0000000022"}, "profit": 4.38}, "LUFFYUSDT": {"sell": {"exchange": "Gateio", "rate": "0.0001313622"}, "buy": {"exchange": "Mexc", "rate": "0.000133732"}, "profit": 1.8}}