{"BOBAUSDT": {"buy": {"exchange": "Huobi", "rate": "0.24451"}, "sell": {"exchange": "Bybit", "rate": "0.2411409"}, "profit": 1.4}, "EGAMEUSDT": {"sell": {"exchange": "Kucoin", "rate": "0.0001116015"}, "buy": {"exchange": "Gateio", "rate": "0.0001130734"}, "profit": 1.32}, "DMTRUSDT": {"buy": {"exchange": "Kucoin", "rate": "0.039980979"}, "sell": {"exchange": "Gateio", "rate": "0.0395084592"}, "profit": 1.2}, "BABYDOGEUSDT": {"buy": {"exchange": "Mexc", "rate": "0.0000000021"}, "sell": {"exchange": "Okx", "rate": "0.0000000021"}, "profit": 3.94}, "EJSUSDT": {"buy": {"exchange": "Gateio", "rate": "0.004533914"}, "sell": {"exchange": "Mexc", "rate": "0.004231446"}, "profit": 7.15}, "LUFFYUSDT": {"sell": {"exchange": "Gateio", "rate": "0.0001283562"}, "buy": {"exchange": "Mexc", "rate": "0.000130239"}, "profit": 1.47}, "CELTUSDT": {"buy": {"exchange": "Mexc", "rate": "0.00068862"}, "sell": {"exchange": "Okx", "rate": "0.000681681"}, "profit": 1.02}}