{"PIASUSDT": {"buy": {"exchange": "Kucoin", "rate": "0.01495503"}, "sell": {"exchange": "Gateio", "rate": "0.01465926"}, "profit": 2.02}, "MANUSDT": {"buy": {"exchange": "Kucoin", "rate": "0.042503454"}, "sell": {"exchange": "Gateio", "rate": "0.039765873"}, "profit": 6.88}, "MIRUSDT": {"sell": {"exchange": "Kucoin", "rate": "0.1114113"}, "buy": {"exchange": "Gateio", "rate": "0.11520912"}, "profit": 3.41}, "BABYDOGEUSDT": {"buy": {"exchange": "Mexc", "rate": "0.0000000021"}, "sell": {"exchange": "Okx", "rate": "0.000000002"}, "profit": 5.2}, "SMARTUSDT": {"buy": {"exchange": "Gateio", "rate": "1.63672"}, "sell": {"exchange": "Mexc", "rate": "1.610214"}, "profit": 1.65}, "DEVTUSDT": {"sell": {"exchange": "Gateio", "rate": "0.00487974"}, "buy": {"exchange": "Mexc", "rate": "0.004933114"}, "profit": 1.09}}