{"ALIUSDT": {"sell": {"exchange": "Huobi", "rate": "0.04072629"}, "buy": {"exchange": "Gateio", "rate": "0.041244346"}, "profit": 1.27}, "MANUSDT": {"buy": {"exchange": "Kucoin", "rate": "0.044171784"}, "sell": {"exchange": "Gateio", "rate": "0.04094673"}, "profit": 7.88}, "DMTRUSDT": {"buy": {"exchange": "Kucoin", "rate": "0.041103855"}, "sell": {"exchange": "Gateio", "rate": "0.040657653"}, "profit": 1.1}, "BABYDOGEUSDT": {"buy": {"exchange": "Mexc", "rate": "0.0000000023"}, "sell": {"exchange": "Okx", "rate": "0.0000000021"}, "profit": 5.79}, "NVIRUSDT": {"buy": {"exchange": "Gateio", "rate": "0.046890032"}, "sell": {"exchange": "Mexc", "rate": "0.04631244"}, "profit": 1.25}, "LUFFYUSDT": {"sell": {"exchange": "Gateio", "rate": "0.0001204404"}, "buy": {"exchange": "Mexc", "rate": "0.000127245"}, "profit": 5.65}}