{"GPTUSDT": {"buy": {"exchange": "Huobi", "rate": "0.0921154"}, "sell": {"exchange": "Mexc", "rate": "0.087675"}, "profit": 5.06}, "PLYUSDT": {"buy": {"exchange": "Huobi", "rate": "0.000660676"}, "sell": {"exchange": "Kucoin", "rate": "0.0006509503"}, "profit": 1.49}, "TOMIUSDT": {"sell": {"exchange": "Huobi", "rate": "2.47494"}, "buy": {"exchange": "Gateio", "rate": "2.51709572"}, "profit": 1.7}, "BRISEUSDT": {"sell": {"exchange": "Gateio", "rate": "0.0000004551"}, "buy": {"exchange": "Mexc", "rate": "0.0000004893"}, "profit": 7.53}, "MCGUSDT": {"sell": {"exchange": "Huobi", "rate": "0.08560086"}, "buy": {"exchange": "Gateio", "rate": "0.08651662"}, "profit": 1.07}, "XENUSDT": {"buy": {"exchange": "Huobi", "rate": "0.0000010978"}, "sell": {"exchange": "Mexc", "rate": "0.0000010633"}, "profit": 3.24}, "GQUSDT": {"buy": {"exchange": "Huobi", "rate": "0.006425124"}, "sell": {"exchange": "Mexc", "rate": "0.006348672"}, "profit": 1.2}, "FLRUSDT": {"sell": {"exchange": "Bybit", "rate": "0.03565562"}, "buy": {"exchange": "Okx", "rate": "0.03603393"}, "profit": 1.06}, "PIASUSDT": {"buy": {"exchange": "Kucoin", "rate": "0.01473525"}, "sell": {"exchange": "Gateio", "rate": "0.01438872"}, "profit": 2.41}, "SCLPUSDT": {"buy": {"exchange": "Kucoin", "rate": "0.2438559"}, "sell": {"exchange": "Gateio", "rate": "0.24094092"}, "profit": 1.21}, "MANUSDT": {"buy": {"exchange": "Kucoin", "rate": "0.043642314"}, "sell": {"exchange": "Gateio", "rate": "0.0404258904"}, "profit": 7.96}, "MIRUSDT": {"sell": {"exchange": "Gateio", "rate": "0.10047054"}, "buy": {"exchange": "Okx", "rate": "0.102897"}, "profit": 2.42}, "RDNTUSDT": {"buy": {"exchange": "Kucoin", "rate": "0.336663"}, "sell": {"exchange": "Okx", "rate": "0.3327324"}, "profit": 1.18}, "BABYDOGEUSDT": {"buy": {"exchange": "Mexc", "rate": "0.0000000022"}, "sell": {"exchange": "Okx", "rate": "0.000000002"}, "profit": 6.43}}