{"MCGUSDT": {"buy": {"exchange": "Huobi", "rate": "0.10615726"}, "sell": {"exchange": "Gateio", "rate": "0.10378716"}, "profit": 2.28}, "KINGUSDT": {"sell": {"exchange": "Kucoin", "rate": "0.01355354"}, "buy": {"exchange": "Gateio", "rate": "0.013733478"}, "profit": 1.33}, "PIASUSDT": {"buy": {"exchange": "Kucoin", "rate": "0.01515483"}, "sell": {"exchange": "Gateio", "rate": "0.01490976"}, "profit": 1.64}, "MANUSDT": {"buy": {"exchange": "Kucoin", "rate": "0.044183772"}, "sell": {"exchange": "Gateio", "rate": "0.0412660674"}, "profit": 7.07}, "CAREUSDT": {"buy": {"exchange": "Kucoin", "rate": "0.0055755189"}, "sell": {"exchange": "Gateio", "rate": "0.005512002"}, "profit": 1.15}, "BRISEUSDT": {"buy": {"exchange": "Kucoin", "rate": "0.0000005329"}, "sell": {"exchange": "Gateio", "rate": "0.0000005191"}, "profit": 2.65}, "REELTUSDT": {"sell": {"exchange": "Gateio", "rate": "0.025809516"}, "buy": {"exchange": "Mexc", "rate": "0.02778432"}, "profit": 7.65}, "BABYDOGEUSDT": {"buy": {"exchange": "Mexc", "rate": "0.0000000021"}, "sell": {"exchange": "Okx", "rate": "0.000000002"}, "profit": 5.82}}