{"CTCUSDT": {"sell": {"exchange": "Huobi", "rate": "0.3721428"}, "buy": {"exchange": "Bybit", "rate": "0.3760236"}, "profit": 1.04}, "RDNTUSDT": {"buy": {"exchange": "Huobi", "rate": "0.456585"}, "sell": {"exchange": "Okx", "rate": "0.4502498"}, "profit": 1.41}, "ALIUSDT": {"sell": {"exchange": "Huobi", "rate": "0.040203246"}, "buy": {"exchange": "Gateio", "rate": "0.040660516"}, "profit": 1.14}, "MANUSDT": {"buy": {"exchange": "Kucoin", "rate": "0.046169784"}, "sell": {"exchange": "Gateio", "rate": "0.0432849972"}, "profit": 6.66}, "BRISEUSDT": {"buy": {"exchange": "Kucoin", "rate": "0.0000004638"}, "sell": {"exchange": "Gateio", "rate": "0.0000004537"}, "profit": 2.24}, "GRAILUSDT": {"sell": {"exchange": "Gateio", "rate": "4234.51212"}, "buy": {"exchange": "Mexc", "rate": "4321.94878"}, "profit": 2.06}, "FNZUSDT": {"sell": {"exchange": "Gateio", "rate": "0.006250476"}, "buy": {"exchange": "Mexc", "rate": "0.0063872"}, "profit": 2.19}, "BABYDOGEUSDT": {"buy": {"exchange": "Mexc", "rate": "0.0000000023"}, "sell": {"exchange": "Okx", "rate": "0.0000000022"}, "profit": 3.71}, "EJSUSDT": {"sell": {"exchange": "Gateio", "rate": "0.00432864"}, "buy": {"exchange": "Mexc", "rate": "0.004378226"}, "profit": 1.15}}