{"MCUSDT": {"buy": {"exchange": "Binance", "rate": "0.291708"}, "sell": {"exchange": "Kucoin", "rate": "0.26661635"}, "profit": 9.41}, "OAXUSDT": {"buy": {"exchange": "Binance", "rate": "0.3697299"}, "sell": {"exchange": "Gateio", "rate": "0.365431404"}, "profit": 1.18}, "EGAMEUSDT": {"buy": {"exchange": "Huobi", "rate": "0.0001183329"}, "sell": {"exchange": "Kucoin", "rate": "0.0001153552"}, "profit": 2.58}, "BRISEUSDT": {"sell": {"exchange": "Gateio", "rate": "0.0000004729"}, "buy": {"exchange": "Mexc", "rate": "0.0000005063"}, "profit": 7.05}, "MANUSDT": {"buy": {"exchange": "Kucoin", "rate": "0.044006949"}, "sell": {"exchange": "Gateio", "rate": "0.0413812974"}, "profit": 6.35}, "HAPIUSDT": {"buy": {"exchange": "Kucoin", "rate": "14.8363488"}, "sell": {"exchange": "Mexc", "rate": "14.63922"}, "profit": 1.35}, "BABYDOGEUSDT": {"buy": {"exchange": "Mexc", "rate": "0.0000000024"}, "sell": {"exchange": "Okx", "rate": "0.0000000023"}, "profit": 2.14}, "HAMUSDT": {"sell": {"exchange": "Gateio", "rate": "0.0000000035"}, "buy": {"exchange": "Mexc", "rate": "0.0000000035"}, "profit": 1.73}, "MIRUSDT": {"sell": {"exchange": "Gateio", "rate": "0.0982962"}, "buy": {"exchange": "Okx", "rate": "0.0999"}, "profit": 1.63}}