{"BETHUSDT": {"sell": {"exchange": "Huobi", "rate": "1703.78076"}, "buy": {"exchange": "Okx", "rate": "1735.25301"}, "profit": 1.85}, "SYSUSDT": {"buy": {"exchange": "Binance", "rate": "0.1766232"}, "sell": {"exchange": "Kucoin", "rate": "0.1747746"}, "profit": 1.06}, "IDUSDT": {"buy": {"exchange": "Kucoin", "rate": "0.51090858"}, "sell": {"exchange": "Mexc", "rate": "0.50388576"}, "profit": 1.39}, "MCGUSDT": {"buy": {"exchange": "Huobi", "rate": "0.0569359"}, "sell": {"exchange": "Gateio", "rate": "0.05603184"}, "profit": 1.61}, "ALIUSDT": {"sell": {"exchange": "Huobi", "rate": "0.035888634"}, "buy": {"exchange": "Gateio", "rate": "0.036349156"}, "profit": 1.28}, "PIASUSDT": {"buy": {"exchange": "Kucoin", "rate": "0.02010987"}, "sell": {"exchange": "Gateio", "rate": "0.01937868"}, "profit": 3.77}, "MANUSDT": {"buy": {"exchange": "Kucoin", "rate": "0.043575381"}, "sell": {"exchange": "Gateio", "rate": "0.0410665692"}, "profit": 6.11}, "BRISEUSDT": {"buy": {"exchange": "Kucoin", "rate": "0.0000004756"}, "sell": {"exchange": "Gateio", "rate": "0.0000004649"}, "profit": 2.3}, "FLYUSDT": {"buy": {"exchange": "Kucoin", "rate": "0.001332666"}, "sell": {"exchange": "Mexc", "rate": "0.0012843636"}, "profit": 3.76}, "OPTIMUSUSDT": {"sell": {"exchange": "Gateio", "rate": "0.42520872"}, "buy": {"exchange": "Mexc", "rate": "0.4632716"}, "profit": 8.95}, "LUFFYUSDT": {"sell": {"exchange": "Gateio", "rate": "0.0001234464"}, "buy": {"exchange": "Mexc", "rate": "0.0001264466"}, "profit": 2.43}, "BABYDOGEUSDT": {"buy": {"exchange": "Mexc", "rate": "0.0000000022"}, "sell": {"exchange": "Okx", "rate": "0.0000000021"}, "profit": 4.26}}