{"ACTUSDT": {"buy": {"exchange": "Huobi", "rate": "0.0012974"}, "sell": {"exchange": "Kucoin", "rate": "0.001279278"}, "profit": 1.42}, "RAINUSDT": {"buy": {"exchange": "Huobi", "rate": "0.002171648"}, "sell": {"exchange": "Mexc", "rate": "0.00213426"}, "profit": 1.75}, "OGVUSDT": {"buy": {"exchange": "Huobi", "rate": "0.006243488"}, "sell": {"exchange": "Mexc", "rate": "0.006148272"}, "profit": 1.55}, "MANUSDT": {"buy": {"exchange": "Kucoin", "rate": "0.041705253"}, "sell": {"exchange": "Gateio", "rate": "0.0391818072"}, "profit": 6.44}, "BRISEUSDT": {"buy": {"exchange": "Kucoin", "rate": "0.0000004464"}, "sell": {"exchange": "Gateio", "rate": "0.0000004409"}, "profit": 1.24}, "EGAMEUSDT": {"sell": {"exchange": "Kucoin", "rate": "0.0001086686"}, "buy": {"exchange": "Gateio", "rate": "0.0001099796"}, "profit": 1.21}, "BABYDOGEUSDT": {"buy": {"exchange": "Mexc", "rate": "0.0000000022"}, "sell": {"exchange": "Okx", "rate": "0.0000000021"}, "profit": 5.7}, "CHOUSDT": {"buy": {"exchange": "Gateio", "rate": "0.65285168"}, "sell": {"exchange": "Mexc", "rate": "0.6431838"}, "profit": 1.5}, "SFGUSDT": {"buy": {"exchange": "Gateio", "rate": "0.018925074"}, "sell": {"exchange": "Okx", "rate": "0.0172172"}, "profit": 9.92}, "CVTUSDT": {"buy": {"exchange": "Mexc", "rate": "0.0004248486"}, "sell": {"exchange": "Okx", "rate": "0.000393393"}, "profit": 8.0}}