{"MCGUSDT": {"sell": {"exchange": "Huobi", "rate": "0.1094685"}, "buy": {"exchange": "Gateio", "rate": "0.11286382"}, "profit": 3.1}, "CAWUSDT": {"sell": {"exchange": "Huobi", "rate": "0.0000000595"}, "buy": {"exchange": "Mexc", "rate": "0.0000000603"}, "profit": 1.35}, "CAREUSDT": {"buy": {"exchange": "Kucoin", "rate": "0.0057211731"}, "sell": {"exchange": "Gateio", "rate": "0.005640258"}, "profit": 1.43}, "BRISEUSDT": {"buy": {"exchange": "Kucoin", "rate": "0.0000005285"}, "sell": {"exchange": "Gateio", "rate": "0.0000005089"}, "profit": 3.84}, "BABYDOGEUSDT": {"buy": {"exchange": "Mexc", "rate": "0.0000000021"}, "sell": {"exchange": "Okx", "rate": "0.000000002"}, "profit": 6.34}, "REELTUSDT": {"sell": {"exchange": "Gateio", "rate": "0.02596182"}, "buy": {"exchange": "Mexc", "rate": "0.02753482"}, "profit": 6.06}}