{"RIFUSDT": {"sell": {"exchange": "Binance", "rate": "0.161161"}, "buy": {"exchange": "Mexc", "rate": "0.1634724"}, "profit": 1.43}, "MANUSDT": {"buy": {"exchange": "Kucoin", "rate": "0.044108847"}, "sell": {"exchange": "Gateio", "rate": "0.0429867018"}, "profit": 2.61}, "RDNTUSDT": {"buy": {"exchange": "Kucoin", "rate": "0.4503492"}, "sell": {"exchange": "Okx", "rate": "0.4126122"}, "profit": 9.15}, "XCADUSDT": {"buy": {"exchange": "Gateio", "rate": "2.10094968"}, "sell": {"exchange": "Mexc", "rate": "2.077647"}, "profit": 1.12}, "FLYUSDT": {"buy": {"exchange": "Kucoin", "rate": "0.001384614"}, "sell": {"exchange": "Mexc", "rate": "0.0013646238"}, "profit": 1.46}, "BABYDOGEUSDT": {"buy": {"exchange": "Mexc", "rate": "0.0000000023"}, "sell": {"exchange": "Okx", "rate": "0.0000000021"}, "profit": 5.19}, "OPTIMUSUSDT": {"sell": {"exchange": "Gateio", "rate": "0.47638086"}, "buy": {"exchange": "Mexc", "rate": "0.4848284"}, "profit": 1.77}, "PSLUSDT": {"buy": {"exchange": "Gateio", "rate": "0.000483032"}, "sell": {"exchange": "Mexc", "rate": "0.00047595"}, "profit": 1.49}}