{"OGVUSDT": {"sell": {"exchange": "Huobi", "rate": "0.00622743"}, "buy": {"exchange": "Kucoin", "rate": "0.006309684"}, "profit": 1.32}, "TRACUSDT": {"sell": {"exchange": "Huobi", "rate": "0.3648282"}, "buy": {"exchange": "Kucoin", "rate": "0.3709287"}, "profit": 1.67}, "ALIUSDT": {"sell": {"exchange": "Huobi", "rate": "0.038866578"}, "buy": {"exchange": "Gateio", "rate": "0.039698444"}, "profit": 2.14}, "CAWUSDT": {"sell": {"exchange": "Huobi", "rate": "0.0000000595"}, "buy": {"exchange": "Mexc", "rate": "0.0000000604"}, "profit": 1.4}, "FLRUSDT": {"sell": {"exchange": "Bybit", "rate": "0.03539536"}, "buy": {"exchange": "Okx", "rate": "0.03580416"}, "profit": 1.15}, "KINGUSDT": {"sell": {"exchange": "Kucoin", "rate": "0.01355354"}, "buy": {"exchange": "Gateio", "rate": "0.013733478"}, "profit": 1.33}, "PIASUSDT": {"buy": {"exchange": "Kucoin", "rate": "0.01513485"}, "sell": {"exchange": "Gateio", "rate": "0.01478952"}, "profit": 2.33}, "MANUSDT": {"buy": {"exchange": "Kucoin", "rate": "0.043869087"}, "sell": {"exchange": "Gateio", "rate": "0.0406913202"}, "profit": 7.81}, "CAREUSDT": {"buy": {"exchange": "Kucoin", "rate": "0.0056948994"}, "sell": {"exchange": "Gateio", "rate": "0.00563625"}, "profit": 1.04}, "BRISEUSDT": {"buy": {"exchange": "Kucoin", "rate": "0.0000005296"}, "sell": {"exchange": "Gateio", "rate": "0.0000005129"}, "profit": 3.25}, "XDBUSDT": {"sell": {"exchange": "Kucoin", "rate": "0.0012783971"}, "buy": {"exchange": "Gateio", "rate": "0.0012912124"}, "profit": 1.0}, "BABYDOGEUSDT": {"buy": {"exchange": "Mexc", "rate": "0.0000000021"}, "sell": {"exchange": "Okx", "rate": "0.000000002"}, "profit": 6.22}, "REELTUSDT": {"sell": {"exchange": "Gateio", "rate": "0.025524948"}, "buy": {"exchange": "Mexc", "rate": "0.0273951"}, "profit": 7.33}}