{"OGVUSDT": {"sell": {"exchange": "Huobi", "rate": "0.00622743"}, "buy": {"exchange": "Kucoin", "rate": "0.006309684"}, "profit": 1.32}, "TRACUSDT": {"sell": {"exchange": "Huobi", "rate": "0.3648282"}, "buy": {"exchange": "Kucoin", "rate": "0.3705291"}, "profit": 1.56}, "TOMIUSDT": {"buy": {"exchange": "Huobi", "rate": "3.0938"}, "sell": {"exchange": "Gateio", "rate": "3.05837454"}, "profit": 1.16}, "ALIUSDT": {"sell": {"exchange": "Huobi", "rate": "0.03898281"}, "buy": {"exchange": "Gateio", "rate": "0.039912016"}, "profit": 2.38}, "CAWUSDT": {"sell": {"exchange": "Huobi", "rate": "0.0000000595"}, "buy": {"exchange": "Mexc", "rate": "0.0000000604"}, "profit": 1.4}, "FLRUSDT": {"sell": {"exchange": "Bybit", "rate": "0.03552549"}, "buy": {"exchange": "Okx", "rate": "0.03601395"}, "profit": 1.37}, "KINGUSDT": {"sell": {"exchange": "Kucoin", "rate": "0.01355354"}, "buy": {"exchange": "Gateio", "rate": "0.01373248"}, "profit": 1.32}, "PIASUSDT": {"buy": {"exchange": "Kucoin", "rate": "0.01513485"}, "sell": {"exchange": "Gateio", "rate": "0.01479954"}, "profit": 2.27}, "MANUSDT": {"buy": {"exchange": "Kucoin", "rate": "0.043869087"}, "sell": {"exchange": "Gateio", "rate": "0.0407321016"}, "profit": 7.7}, "BRISEUSDT": {"buy": {"exchange": "Kucoin", "rate": "0.0000005318"}, "sell": {"exchange": "Gateio", "rate": "0.000000514"}, "profit": 3.46}, "REELTUSDT": {"sell": {"exchange": "Gateio", "rate": "0.025628154"}, "buy": {"exchange": "Mexc", "rate": "0.0273951"}, "profit": 6.89}, "BABYDOGEUSDT": {"buy": {"exchange": "Mexc", "rate": "0.0000000021"}, "sell": {"exchange": "Okx", "rate": "0.000000002"}, "profit": 6.27}}