{"TOMIUSDT": {"buy": {"exchange": "Huobi", "rate": "3.1589694"}, "sell": {"exchange": "Mexc", "rate": "3.0674226"}, "profit": 2.98}, "XENUSDT": {"buy": {"exchange": "Huobi", "rate": "0.0000012176"}, "sell": {"exchange": "Mexc", "rate": "0.0000011899"}, "profit": 2.33}, "INSURUSDT": {"buy": {"exchange": "Huobi", "rate": "0.076846"}, "sell": {"exchange": "Mexc", "rate": "0.0759516"}, "profit": 1.18}, "CAWUSDT": {"sell": {"exchange": "Huobi", "rate": "0.0000000595"}, "buy": {"exchange": "Mexc", "rate": "0.0000000603"}, "profit": 1.23}, "EVMOSUSDT": {"buy": {"exchange": "Huobi", "rate": "0.349799"}, "sell": {"exchange": "Mexc", "rate": "0.3462912"}, "profit": 1.01}, "KINGUSDT": {"sell": {"exchange": "Kucoin", "rate": "0.01355354"}, "buy": {"exchange": "Gateio", "rate": "0.013733478"}, "profit": 1.33}, "PIASUSDT": {"buy": {"exchange": "Kucoin", "rate": "0.01515483"}, "sell": {"exchange": "Gateio", "rate": "0.01488972"}, "profit": 1.78}, "MANUSDT": {"buy": {"exchange": "Kucoin", "rate": "0.044147808"}, "sell": {"exchange": "Gateio", "rate": "0.042084"}, "profit": 4.9}, "REELTUSDT": {"sell": {"exchange": "Gateio", "rate": "0.025883664"}, "buy": {"exchange": "Mexc", "rate": "0.0276446"}, "profit": 6.8}, "BABYDOGEUSDT": {"buy": {"exchange": "Mexc", "rate": "0.0000000021"}, "sell": {"exchange": "Okx", "rate": "0.000000002"}, "profit": 6.04}}