{"SYSUSDT": {"buy": {"exchange": "Binance", "rate": "0.1744254"}, "sell": {"exchange": "Kucoin", "rate": "0.1726725"}, "profit": 1.02}, "TITANUSDT": {"sell": {"exchange": "Huobi", "rate": "0.057759288"}, "buy": {"exchange": "Kucoin", "rate": "0.05837157"}, "profit": 1.06}, "ARBUSDT": {"sell": {"exchange": "Mexc", "rate": "1.1278512"}, "buy": {"exchange": "Okx", "rate": "1.1527461"}, "profit": 2.21}, "ALIUSDT": {"sell": {"exchange": "Huobi", "rate": "0.03591168"}, "buy": {"exchange": "Gateio", "rate": "0.036421012"}, "profit": 1.42}, "BETHUSDT": {"sell": {"exchange": "Huobi", "rate": "1710.75468"}, "buy": {"exchange": "Okx", "rate": "1732.266"}, "profit": 1.26}, "KINGUSDT": {"buy": {"exchange": "Kucoin", "rate": "0.01630368"}, "sell": {"exchange": "Gateio", "rate": "0.016059054"}, "profit": 1.52}, "PIASUSDT": {"buy": {"exchange": "Kucoin", "rate": "0.01995003"}, "sell": {"exchange": "Gateio", "rate": "0.0192885"}, "profit": 3.43}, "MANUSDT": {"buy": {"exchange": "Kucoin", "rate": "0.039858102"}, "sell": {"exchange": "Gateio", "rate": "0.0379669824"}, "profit": 4.98}, "BRISEUSDT": {"buy": {"exchange": "Kucoin", "rate": "0.0000004651"}, "sell": {"exchange": "Gateio", "rate": "0.0000004581"}, "profit": 1.55}, "GRAILUSDT": {"sell": {"exchange": "Gateio", "rate": "3672.33"}, "buy": {"exchange": "Mexc", "rate": "3740.504"}, "profit": 1.86}, "FLYUSDT": {"buy": {"exchange": "Kucoin", "rate": "0.001315683"}, "sell": {"exchange": "Mexc", "rate": "0.0012937824"}, "profit": 1.69}, "BABYDOGEUSDT": {"buy": {"exchange": "Mexc", "rate": "0.0000000021"}, "sell": {"exchange": "Okx", "rate": "0.000000002"}, "profit": 5.31}, "LUFFYUSDT": {"sell": {"exchange": "Gateio", "rate": "0.000125751"}, "buy": {"exchange": "Mexc", "rate": "0.000129241"}, "profit": 2.78}}